{
  "process": "sdaemon.exe",
  "pollInterval": 16,
  "outputs": [
    {
      "label": "Start Lamp",
      "type": "Byte",
      "offset": "0x14D14A5",
      "script": "(value & 0xFF)",
      "address": "",
      "notes": "",
      "invert": false,
      "format": "{value}",
      "useModuleOffset": true,
      "moduleName": "sdaemon.exe",
      "offsets": [],
      "isPointerChain": false,
      "bitmask": "0xFF",
      "bitwiseOp": "AND",
      "bitfield": true
    },
    {
      "label": "View1 Lamp",
      "type": "Byte",
      "offset": "0x14D14AD",
      "script": "(value & 0xFF)",
      "address": "",
      "notes": "",
      "invert": false,
      "format": "{value}",
      "useModuleOffset": true,
      "moduleName": "sdaemon.exe",
      "offsets": [],
      "isPointerChain": false,
      "bitmask": "0xFF",
      "bitwiseOp": "AND",
      "bitfield": true
    },
    {
      "label": "View2 Lamp",
      "type": "Byte",
      "offset": "0x14D14B1",
      "script": "(value & 0xFF)",
      "address": "",
      "notes": "",
      "invert": false,
      "format": "{value}",
      "useModuleOffset": true,
      "moduleName": "sdaemon.exe",
      "offsets": [],
      "isPointerChain": false,
      "bitmask": "0xFF",
      "bitwiseOp": "AND",
      "bitfield": true
    },
    {
      "label": "View3 Lamp",
      "type": "Byte",
      "offset": "0x14D14B5",
      "script": "(value & 0xFF)",
      "address": "",
      "notes": "",
      "invert": false,
      "format": "{value}",
      "useModuleOffset": true,
      "moduleName": "sdaemon.exe",
      "offsets": [],
      "isPointerChain": false,
      "bitmask": "0xFF",
      "bitwiseOp": "AND",
      "bitfield": true
    },
    {
      "label": "Seat Base Lamp",
      "type": "Byte",
      "offset": "0x14D14D1",
      "script": "(value & 0xFF)",
      "address": "",
      "notes": "",
      "invert": false,
      "format": "{value}",
      "useModuleOffset": true,
      "moduleName": "sdaemon.exe",
      "offsets": [],
      "isPointerChain": false,
      "bitmask": "0xFF",
      "bitwiseOp": "AND",
      "bitfield": true
    },
    {
      "label": "Seat Backrest Lamp",
      "type": "Byte",
      "offset": "0x14D14D5",
      "script": "(value & 0xFF)",
      "address": "",
      "notes": "",
      "invert": false,
      "format": "{value}",
      "useModuleOffset": true,
      "moduleName": "sdaemon.exe",
      "offsets": [],
      "isPointerChain": false,
      "bitmask": "0xFF",
      "bitwiseOp": "AND",
      "bitfield": true
    }
  ]
}